README.rst
setup.py
django_bleach/__init__.py
django_bleach/forms.py
django_bleach/models.py
django_bleach/utils.py
django_bleach/templatetags/__init__.py
django_bleach/templatetags/bleach_tags.py
mysociety_django_bleach.egg-info/PKG-INFO
mysociety_django_bleach.egg-info/SOURCES.txt
mysociety_django_bleach.egg-info/dependency_links.txt
mysociety_django_bleach.egg-info/requires.txt
mysociety_django_bleach.egg-info/top_level.txt