Metadata-Version: 1.1
Name: mysociety-django-bleach
Version: 0.2.0
Summary: Easily use bleach with Django models and templates
Home-page: https://bitbucket.org/ionata/django-bleach
Author: Tim Heap
Author-email: heap.tim@gmail.com
License: UNKNOWN
Platform: UNKNOWN
Classifier: Environment :: Web Environment
Classifier: Intended Audience :: Developers
Classifier: Operating System :: OS Independent
Classifier: Programming Language :: Python
Classifier: Framework :: Django
